deepint/__init__.py
deepint/auth/__init__.py
deepint/auth/credentials.py
deepint/core/__init__.py
deepint/core/alert.py
deepint/core/dashboard.py
deepint/core/model.py
deepint/core/organization.py
deepint/core/source.py
deepint/core/task.py
deepint/core/visualization.py
deepint/core/workspace.py
deepint/error/__init__.py
deepint/error/errors.py
deepint/util/__init__.py
deepint/util/parser.py
deepint/util/request.py
deepint-1.4.3.dist-info/LICENSE.txt
deepint-1.4.3.dist-info/METADATA
deepint-1.4.3.dist-info/WHEEL
deepint-1.4.3.dist-info/top_level.txt
deepint-1.4.3.dist-info/RECORD
