Metadata-Version: 2.1
Name: deepint
Version: 1.4.3
Summary: deepint is a python package to work with Deep Intelligence in a more easy and intuitive way.
Home-page: https://deepint.net/
Author: Deep Intelligence
Author-email: devs@deepint.net
License: Copyright
Download-URL: https://github.com/deepintdev/deepint-python-SDK/archive/master.zip
Project-URL: Bug Reports, https://github.com/deepintdev/deepint-python-SDK/issues
Project-URL: Source, https://github.com/deepintdev/deepint-python-SDK
Project-URL: Documentation, https://deepint-python-sdk.readthedocs.io/en/latest/index.html
Keywords: deepint,Deep Intelligence,datawarehouse,analysis,big data,IoT,Industry 4.0,Healthcare,smart cities
Platform: UNKNOWN
Classifier: Development Status :: 5 - Production/Stable
Classifier: Programming Language :: Python :: 3 :: Only
Classifier: Programming Language :: Python :: 3.7
Classifier: Programming Language :: Python :: 3.8
Classifier: Programming Language :: Python :: 3.9
Classifier: Intended Audience :: Developers
Classifier: Topic :: Scientific/Engineering :: Artificial Intelligence
Classifier: Topic :: Database :: Database Engines/Servers
Classifier: Topic :: Scientific/Engineering :: Visualization
Classifier: Topic :: Scientific/Engineering :: Information Analysis
Classifier: Topic :: Software Development :: Libraries
Requires-Python: >=3
License-File: LICENSE.txt
Requires-Dist: asyncio (>=3.4.3)
Requires-Dist: configparser (>=5.0.1)
Requires-Dist: numpy (>=1.18.3)
Requires-Dist: pandas (>=1.1.4)
Requires-Dist: python-dateutil (>=2.8.1)
Requires-Dist: requests (>=2.24.0)
Requires-Dist: urllib3 (>=1.25.9)
Provides-Extra: docs
Requires-Dist: jinja2 (<3.1) ; extra == 'docs'
Requires-Dist: numpy (==1.22.0) ; extra == 'docs'
Requires-Dist: pandas (==1.1.4) ; extra == 'docs'
Requires-Dist: recommonmark (==0.6.0) ; extra == 'docs'
Requires-Dist: sphinx (==5.3.0) ; extra == 'docs'
Requires-Dist: sphinx-rtd-theme (==0.4.3) ; extra == 'docs'
Provides-Extra: tests
Requires-Dist: codecov ; extra == 'tests'
Requires-Dist: pytest ; extra == 'tests'
Requires-Dist: pytest-cov ; extra == 'tests'
